trading_ig/__init__.py
trading_ig/config.py
trading_ig/lightstreamer.py
trading_ig/rest.py
trading_ig/stream.py
trading_ig/utils.py
trading_ig-0.0.21.dist-info/LICENSE
trading_ig-0.0.21.dist-info/METADATA
trading_ig-0.0.21.dist-info/WHEEL
trading_ig-0.0.21.dist-info/RECORD
