Metadata-Version: 2.1
Name: trading-ig
Version: 0.0.21
Summary: A lightweight Python wrapper for the IG Markets API
Home-page: https://github.com/ig-python/trading-ig
License: BSD-3-Clause
Keywords: trading,spread betting,CFDs
Author: Femto Trader
Author-email: femto.trader@gmail.com
Maintainer: Andy Geach
Maintainer-email: andy@bugorfeature.net
Requires-Python: >=3.7,<4.0
Classifier: Development Status :: 3 - Alpha
Classifier: Environment :: Console
Classifier: Intended Audience :: Developers
Classifier: Intended Audience :: Science/Research
Classifier: License :: OSI Approved :: BSD License
Classifier: Operating System :: OS Independent
Classifier: Programming Language :: Cython
Classifier: Programming Language :: Python
Classifier: Programming Language :: Python :: 3
Classifier: Programming Language :: Python :: 3.7
Classifier: Programming Language :: Python :: 3.8
Classifier: Programming Language :: Python :: 3.9
Classifier: Programming Language :: Python :: 3.10
Classifier: Programming Language :: Python :: 3.11
Classifier: Topic :: Scientific/Engineering
Classifier: Topic :: Software Development :: Libraries
Provides-Extra: docs
Provides-Extra: munch
Provides-Extra: pandas
Provides-Extra: sphinx
Provides-Extra: tenacity
Requires-Dist: lightstreamer-client-lib (>=1.0.3,<2.0.0)
Requires-Dist: munch (>=2.5,<3.0) ; extra == "munch"
Requires-Dist: pandas (>=1,<2) ; extra == "pandas"
Requires-Dist: pycryptodome (>=3.9,<4.0)
Requires-Dist: requests (>=2.24,<3.0)
Requires-Dist: requests-cache (>=0.5,<0.6)
Requires-Dist: six (>=1.15,<2.0)
Requires-Dist: tenacity (>=8,<9) ; extra == "tenacity"
Project-URL: Documentation, https://trading-ig.readthedocs.io/
Project-URL: Issues, https://github.com/ig-python/trading-ig/issues
Project-URL: Repository, https://github.com/ig-python/trading-ig
